bayes-vi/__init__.py
bayes_vi/__init__.py
bayes_vi/inference/__init__.py
bayes_vi/inference/inference.py
bayes_vi/inference/mcmc/__init__.py
bayes_vi/inference/mcmc/mcmc.py
bayes_vi/inference/mcmc/sample_results.py
bayes_vi/inference/mcmc/stepsize_adaptation_kernels.py
bayes_vi/inference/mcmc/transition_kernels.py
bayes_vi/inference/point_estimate/__init__.py
bayes_vi/inference/variational_sdg/__init__.py
bayes_vi/inference/vi/__init__.py
bayes_vi/inference/vi/flow_bijectors.py
bayes_vi/inference/vi/surrogate_posteriors.py
bayes_vi/inference/vi/vi.py
bayes_vi/model/__init__.py
bayes_vi/model/model.py
bayes_vi/models/__init__.py
bayes_vi/utils/__init__.py
bayes_vi/utils/bijectors.py
bayes_vi/utils/datasets.py
bayes_vi/utils/leapfrog_integrator.py
bayes_vi/utils/sample_results.py
bayes_vi/utils/symplectic_integrators.py
bayes_vi-0.3.0.dist-info/LICENSE
bayes_vi-0.3.0.dist-info/METADATA
bayes_vi-0.3.0.dist-info/WHEEL
bayes_vi-0.3.0.dist-info/top_level.txt
bayes_vi-0.3.0.dist-info/RECORD
