Metadata-Version: 2.1
Name: bayes-vi
Version: 0.3.0
Summary: A package for bayesian inference
Home-page: https://github.com/MaxGrtz/bayesian-inference
Author: Maximilian Gartz
Author-email: maximilian.gartz@outlook.de
License: UNKNOWN
Platform: UNKNOWN
Classifier: Programming Language :: Python :: 3
Classifier: License :: OSI Approved :: MIT License
Classifier: Operating System :: OS Independent
Requires-Python: >=3.6
Requires-Dist: numpy (==1.19.5)
Requires-Dist: pandas (>=1.1.5)
Requires-Dist: tensorflow (>=2.4.1)
Requires-Dist: tensorflow-probability (>=0.12.1)
Requires-Dist: fastprogress (>=1.0.0)
